{
  "omega": {
    "etuTargetTime": 1818739833359,
    "riskPremium": 142.5,
    "events": [
      {
        "id": "1766903014629-h2vv1j9",
        "text": "[TRIGGER] Trade executed: 18.24 @ 29106974.73 by bot_user_xu5dm2",
        "impact": "NEUTRAL",
        "timestamp": 1766903014629
      },
      {
        "id": "1766903008760-uyiw5b8",
        "text": "[TRIGGER] Trade executed: 43.58 @ 29109171.82 by bot_user_31hgie",
        "impact": "NEUTRAL",
        "timestamp": 1766903008760
      },
      {
        "id": "1766903005012-26rxd76",
        "text": "[TRIGGER] Trade executed: 91.25 @ 29195975.91 by bot_user_k8mgvc",
        "impact": "NEUTRAL",
        "timestamp": 1766903005012
      },
      {
        "id": "1766902991076-twzz4w1",
        "text": "[TRIGGER] Trade executed: 13.57 @ 28972096.61 by bot_user_pjovec",
        "impact": "NEUTRAL",
        "timestamp": 1766902991076
      },
      {
        "id": "1766902984027-isbburz",
        "text": "[TRIGGER] Trade executed: 0.65 @ 28688425.01 by bot_user_4b38w3",
        "impact": "NEUTRAL",
        "timestamp": 1766902984027
      },
      {
        "id": "1766902981229-3ajdgds",
        "text": "[TRIGGER] Trade executed: 55.84 @ 28694649.08 by bot_user_3zkmg1",
        "impact": "NEUTRAL",
        "timestamp": 1766902981229
      },
      {
        "id": "1766902978586-nyiatjv",
        "text": "[TRIGGER] Trade executed: 12.47 @ 28892433.25 by bot_user_bijus7",
        "impact": "NEUTRAL",
        "timestamp": 1766902978586
      },
      {
        "id": "1766902975288-cr3qif1",
        "text": "[TRIGGER] Trade executed: 37.48 @ 29626813.65 by bot_user_3z2ccu",
        "impact": "NEUTRAL",
        "timestamp": 1766902975288
      }
    ],
    "alertMessage": "⚠ SYSTEM ALERT: GEOPOLITICAL TENSION RISING"
  },
  "market": {
    "currentPrice": 28792318.69,
    "priceChange24h": 0,
    "volume24h": 1276126712008.6584,
    "marketIndex": "STRONG BUY",
    "klineData": [
      {
        "id": 60,
        "timestamp": 1766902927605,
        "open": 29361017.51,
        "high": 29786651.27,
        "low": 29037911.21,
        "close": 29037911.21,
        "volume": 46.0927
      },
      {
        "id": 60,
        "timestamp": 1766902929126,
        "open": 29786651.27,
        "high": 29786651.27,
        "low": 29786651.27,
        "close": 29786651.27,
        "volume": 0
      },
      {
        "id": 60,
        "timestamp": 1766902930632,
        "open": 29786651.27,
        "high": 28875862.43,
        "low": 28809051.8,
        "close": 28875862.43,
        "volume": 100.0692
      },
      {
        "id": 60,
        "timestamp": 1766902932147,
        "open": 28809051.8,
        "high": 28809051.8,
        "low": 28809051.8,
        "close": 28809051.8,
        "volume": 0
      },
      {
        "id": 60,
        "timestamp": 1766902933723,
        "open": 28809051.8,
        "high": 28929055.59,
        "low": 28809051.8,
        "close": 28929055.59,
        "volume": 92.6114
      },
      {
        "id": 60,
        "timestamp": 1766902935225,
        "open": 28809051.8,
        "high": 28809051.8,
        "low": 28809051.8,
        "close": 28809051.8,
        "volume": 0
      },
      {
        "id": 60,
        "timestamp": 1766902936738,
        "open": 28809051.8,
        "high": 28809051.8,
        "low": 28694649.08,
        "close": 28809051.8,
        "volume": 66.7038
      },
      {
        "id": 60,
        "timestamp": 1766902938251,
        "open": 28694649.08,
        "high": 28694649.08,
        "low": 28694649.08,
        "close": 28694649.08,
        "volume": 0
      },
      {
        "id": 60,
        "timestamp": 1766902939836,
        "open": 28694649.08,
        "high": 28694649.08,
        "low": 28694649.08,
        "close": 28694649.08,
        "volume": 0
      },
      {
        "id": 60,
        "timestamp": 1766902941343,
        "open": 28694649.08,
        "high": 28694649.08,
        "low": 28694649.08,
        "close": 28694649.08,
        "volume": 0
      },
      {
        "id": 60,
        "timestamp": 1766902942867,
        "open": 28694649.08,
        "high": 28694649.08,
        "low": 28694649.08,
        "close": 28694649.08,
        "volume": 0
      },
      {
        "id": 60,
        "timestamp": 1766902944363,
        "open": 28694649.08,
        "high": 29820641.93,
        "low": 29786651.27,
        "close": 29786651.27,
        "volume": 33.4201
      },
      {
        "id": 60,
        "timestamp": 1766902945865,
        "open": 29820641.93,
        "high": 29820641.93,
        "low": 29820641.93,
        "close": 29820641.93,
        "volume": 0
      },
      {
        "id": 60,
        "timestamp": 1766902947408,
        "open": 29820641.93,
        "high": 29820641.93,
        "low": 29820641.93,
        "close": 29820641.93,
        "volume": 59.9827
      },
      {
        "id": 60,
        "timestamp": 1766902948928,
        "open": 29820641.93,
        "high": 29820641.93,
        "low": 29820641.93,
        "close": 29820641.93,
        "volume": 0
      },
      {
        "id": 60,
        "timestamp": 1766902950438,
        "open": 29820641.93,
        "high": 29821207.24,
        "low": 29820641.93,
        "close": 29820641.93,
        "volume": 65.219
      },
      {
        "id": 60,
        "timestamp": 1766902951945,
        "open": 29821207.24,
        "high": 29821207.24,
        "low": 29821207.24,
        "close": 29821207.24,
        "volume": 0
      },
      {
        "id": 60,
        "timestamp": 1766902953489,
        "open": 29821207.24,
        "high": 29821207.24,
        "low": 29821207.24,
        "close": 29821207.24,
        "volume": 0
      },
      {
        "id": 60,
        "timestamp": 1766902955006,
        "open": 29821207.24,
        "high": 29821207.24,
        "low": 29821207.24,
        "close": 29821207.24,
        "volume": 0
      },
      {
        "id": 60,
        "timestamp": 1766902956509,
        "open": 29821207.24,
        "high": 29626813.65,
        "low": 29626813.65,
        "close": 29626813.65,
        "volume": 13.999
      },
      {
        "id": 60,
        "timestamp": 1766902958026,
        "open": 29626813.65,
        "high": 29626813.65,
        "low": 29626813.65,
        "close": 29626813.65,
        "volume": 0
      },
      {
        "id": 60,
        "timestamp": 1766902959619,
        "open": 29626813.65,
        "high": 29873737.5,
        "low": 29821207.24,
        "close": 29821207.24,
        "volume": 94.1128
      },
      {
        "id": 60,
        "timestamp": 1766902961105,
        "open": 29873737.5,
        "high": 29873737.5,
        "low": 29873737.5,
        "close": 29873737.5,
        "volume": 0
      },
      {
        "id": 60,
        "timestamp": 1766902962609,
        "open": 29873737.5,
        "high": 29626813.65,
        "low": 29626813.65,
        "close": 29626813.65,
        "volume": 49.5201
      },
      {
        "id": 60,
        "timestamp": 1766902964161,
        "open": 29626813.65,
        "high": 29626813.65,
        "low": 29626813.65,
        "close": 29626813.65,
        "volume": 0
      },
      {
        "id": 60,
        "timestamp": 1766902965679,
        "open": 29626813.65,
        "high": 29626813.65,
        "low": 29626813.65,
        "close": 29626813.65,
        "volume": 0
      },
      {
        "id": 60,
        "timestamp": 1766902967183,
        "open": 29626813.65,
        "high": 29626813.65,
        "low": 29626813.65,
        "close": 29626813.65,
        "volume": 0
      },
      {
        "id": 60,
        "timestamp": 1766902968688,
        "open": 29626813.65,
        "high": 29873737.5,
        "low": 29873737.5,
        "close": 29873737.5,
        "volume": 53.3952
      },
      {
        "id": 60,
        "timestamp": 1766902970190,
        "open": 29873737.5,
        "high": 29873737.5,
        "low": 29873737.5,
        "close": 29873737.5,
        "volume": 0
      },
      {
        "id": 60,
        "timestamp": 1766902971802,
        "open": 29873737.5,
        "high": 29873737.5,
        "low": 29873737.5,
        "close": 29873737.5,
        "volume": 0
      },
      {
        "id": 60,
        "timestamp": 1766902973382,
        "open": 29873737.5,
        "high": 29873737.5,
        "low": 29873737.5,
        "close": 29873737.5,
        "volume": 0
      },
      {
        "id": 60,
        "timestamp": 1766902974889,
        "open": 29873737.5,
        "high": 29873737.5,
        "low": 29873737.5,
        "close": 29873737.5,
        "volume": 0
      },
      {
        "id": 60,
        "timestamp": 1766902976417,
        "open": 29873737.5,
        "high": 29626813.65,
        "low": 28892433.25,
        "close": 29626813.65,
        "volume": 105.3538
      },
      {
        "id": 60,
        "timestamp": 1766902978033,
        "open": 28892433.25,
        "high": 28892433.25,
        "low": 28892433.25,
        "close": 28892433.25,
        "volume": 0
      },
      {
        "id": 60,
        "timestamp": 1766902979536,
        "open": 28892433.25,
        "high": 28892433.25,
        "low": 28694649.08,
        "close": 28892433.25,
        "volume": 15.394
      },
      {
        "id": 60,
        "timestamp": 1766902981261,
        "open": 28892433.25,
        "high": 28694649.08,
        "low": 28688425.01,
        "close": 28694649.08,
        "volume": 58.7276
      },
      {
        "id": 60,
        "timestamp": 1766902982771,
        "open": 28688425.01,
        "high": 28688425.01,
        "low": 28688425.01,
        "close": 28688425.01,
        "volume": 0
      },
      {
        "id": 60,
        "timestamp": 1766902984275,
        "open": 28688425.01,
        "high": 28688425.01,
        "low": 28597270.08,
        "close": 28688425.01,
        "volume": 52.6667
      },
      {
        "id": 60,
        "timestamp": 1766902985795,
        "open": 28597270.08,
        "high": 28597270.08,
        "low": 28597270.08,
        "close": 28597270.08,
        "volume": 0
      },
      {
        "id": 60,
        "timestamp": 1766902987302,
        "open": 28597270.08,
        "high": 28597270.08,
        "low": 28597270.08,
        "close": 28597270.08,
        "volume": 0
      },
      {
        "id": 60,
        "timestamp": 1766902988815,
        "open": 28597270.08,
        "high": 28597270.08,
        "low": 28597270.08,
        "close": 28597270.08,
        "volume": 0
      },
      {
        "id": 60,
        "timestamp": 1766902990317,
        "open": 28597270.08,
        "high": 28597270.08,
        "low": 28597270.08,
        "close": 28597270.08,
        "volume": 0
      },
      {
        "id": 60,
        "timestamp": 1766902991823,
        "open": 28597270.08,
        "high": 28972096.61,
        "low": 28597270.08,
        "close": 28972096.61,
        "volume": 23.5259
      },
      {
        "id": 60,
        "timestamp": 1766902993328,
        "open": 28597270.08,
        "high": 28597270.08,
        "low": 28597270.08,
        "close": 28597270.08,
        "volume": 0
      },
      {
        "id": 60,
        "timestamp": 1766902994838,
        "open": 28597270.08,
        "high": 28597270.08,
        "low": 28597270.08,
        "close": 28597270.08,
        "volume": 0
      },
      {
        "id": 60,
        "timestamp": 1766902996369,
        "open": 28597270.08,
        "high": 28597270.08,
        "low": 28597270.08,
        "close": 28597270.08,
        "volume": 0
      },
      {
        "id": 60,
        "timestamp": 1766902997882,
        "open": 28597270.08,
        "high": 28597270.08,
        "low": 28597270.08,
        "close": 28597270.08,
        "volume": 0
      },
      {
        "id": 60,
        "timestamp": 1766902999461,
        "open": 28597270.08,
        "high": 28597270.08,
        "low": 28597270.08,
        "close": 28597270.08,
        "volume": 0
      },
      {
        "id": 60,
        "timestamp": 1766903001008,
        "open": 28597270.08,
        "high": 28597270.08,
        "low": 28597270.08,
        "close": 28597270.08,
        "volume": 0
      },
      {
        "id": 60,
        "timestamp": 1766903002520,
        "open": 28597270.08,
        "high": 28597270.08,
        "low": 28597270.08,
        "close": 28597270.08,
        "volume": 0
      },
      {
        "id": 60,
        "timestamp": 1766903004025,
        "open": 28597270.08,
        "high": 28597270.08,
        "low": 28597270.08,
        "close": 28597270.08,
        "volume": 0
      },
      {
        "id": 60,
        "timestamp": 1766903005534,
        "open": 28597270.08,
        "high": 29195975.91,
        "low": 29109171.82,
        "close": 29195975.91,
        "volume": 99.775
      },
      {
        "id": 60,
        "timestamp": 1766903007039,
        "open": 29109171.82,
        "high": 29109171.82,
        "low": 29109171.82,
        "close": 29109171.82,
        "volume": 0
      },
      {
        "id": 60,
        "timestamp": 1766903008540,
        "open": 29109171.82,
        "high": 29109171.82,
        "low": 29109171.82,
        "close": 29109171.82,
        "volume": 0
      },
      {
        "id": 60,
        "timestamp": 1766903010048,
        "open": 29109171.82,
        "high": 29109171.82,
        "low": 29106974.73,
        "close": 29109171.82,
        "volume": 109.6346
      },
      {
        "id": 60,
        "timestamp": 1766903011562,
        "open": 29106974.73,
        "high": 29106974.73,
        "low": 29106974.73,
        "close": 29106974.73,
        "volume": 0
      },
      {
        "id": 60,
        "timestamp": 1766903013074,
        "open": 29106974.73,
        "high": 29106974.73,
        "low": 29106974.73,
        "close": 29106974.73,
        "volume": 0
      },
      {
        "id": 60,
        "timestamp": 1766903014649,
        "open": 29106974.73,
        "high": 29106974.73,
        "low": 28792318.69,
        "close": 29106974.73,
        "volume": 20.9023
      },
      {
        "id": 60,
        "timestamp": 1766903016159,
        "open": 28792318.69,
        "high": 28792318.69,
        "low": 28792318.69,
        "close": 28792318.69,
        "volume": 0
      },
      {
        "id": 60,
        "timestamp": 1766903017664,
        "open": 28792318.69,
        "high": 28792318.69,
        "low": 28792318.69,
        "close": 28792318.69,
        "volume": 0
      }
    ],
    "orderBook": {
      "asks": [
        {
          "price": 29769561.51,
          "amount": 26.6811
        },
        {
          "price": 29873737.5,
          "amount": 5.36220000000003
        },
        {
          "price": 29893766.16,
          "amount": 30.3045
        },
        {
          "price": 29937230.44,
          "amount": 102.6375
        },
        {
          "price": 29946676.47,
          "amount": 82.4942
        },
        {
          "price": 30001118.6,
          "amount": 81.4101
        },
        {
          "price": 30017554.18,
          "amount": 26.3178
        },
        {
          "price": 30049721.04,
          "amount": 84.8869
        },
        {
          "price": 30059885.02,
          "amount": 15.2063
        },
        {
          "price": 30196994.76,
          "amount": 94.7523
        }
      ],
      "bids": [
        {
          "price": 28792318.69,
          "amount": 15.966599999999993
        },
        {
          "price": 28597270.08,
          "amount": 7.930100000000035
        },
        {
          "price": 28584000.08,
          "amount": 33.9624
        },
        {
          "price": 28567302.71,
          "amount": 45.4059
        },
        {
          "price": 28534450.08,
          "amount": 83.4957
        },
        {
          "price": 28526021.79,
          "amount": 69.0444
        },
        {
          "price": 28500742.09,
          "amount": 103.9464
        },
        {
          "price": 28438643.29,
          "amount": 11.5235
        },
        {
          "price": 28411691.89,
          "amount": 36.2468
        },
        {
          "price": 28358902.58,
          "amount": 70.1218
        }
      ]
    },
    "recentTrades": [],
    "updatedAt": 1766903018312
  },
  "map": {
    "taiwan": {
      "nodeCount": 13266,
      "logs": [
        {
          "id": "1766903017319-ophz4we",
          "message": "[CONNECT] Taipei (Xinyi) :: bot_user_6mqgv0 (0x846854...)",
          "timestamp": 1766903017319,
          "nodeId": "NODE-9B7J4A",
          "city": "Taipei (Xinyi)",
          "location": {
            "lat": 25.01983124923046,
            "lng": 121.5490522082114
          },
          "status": "active",
          "connectionType": "relay"
        },
        {
          "id": "1766903016515-fjinbgu",
          "message": "[CONNECT] Taichung :: bot_user_fh87h0 (0xa9B811...)",
          "timestamp": 1766903016515,
          "nodeId": "NODE-G79DJA",
          "city": "Taichung",
          "location": {
            "lat": 24.16465477890027,
            "lng": 120.66410796391962
          },
          "status": "active",
          "connectionType": "direct"
        },
        {
          "id": "1766903014821-234g5ly",
          "message": "[CONNECT] New Taipei :: bot_user_3k3jqv (0x3e8dDb...)",
          "timestamp": 1766903014822,
          "nodeId": "NODE-GLLB3K",
          "city": "New Taipei",
          "location": {
            "lat": 25.019788364841148,
            "lng": 121.4773728205294
          },
          "status": "active",
          "connectionType": "relay"
        },
        {
          "id": "1766903009089-gbstqhj",
          "message": "[CONNECT] Tainan :: bot_user_vb7n6x (0x3E903b...)",
          "timestamp": 1766903009089,
          "nodeId": "NODE-8KTXHE",
          "city": "Tainan",
          "location": {
            "lat": 22.98806271613571,
            "lng": 120.22285506984778
          },
          "status": "active",
          "connectionType": "relay"
        },
        {
          "id": "1766903004147-b4xtlsm",
          "message": "[CONNECT] Hsinchu (Science Park) :: bot_user_9o3hv1 (0xdC4819...)",
          "timestamp": 1766903004147,
          "nodeId": "NODE-29XQTS",
          "city": "Hsinchu (Science Park)",
          "location": {
            "lat": 24.807101567754703,
            "lng": 120.98509835203548
          },
          "status": "active",
          "connectionType": "direct"
        },
        {
          "id": "1766903002532-s9yxxyi",
          "message": "[CONNECT] Tainan :: bot_user_351u3a (0x77Cf60...)",
          "timestamp": 1766903002533,
          "nodeId": "NODE-IP2RKK",
          "city": "Tainan",
          "location": {
            "lat": 22.997875841782882,
            "lng": 120.22902022644999
          },
          "status": "active",
          "connectionType": "direct"
        }
      ]
    },
    "mainland": {
      "assetPoolValue": 1425391014,
      "unitCount": 43529,
      "logs": [
        {
          "id": "1766903016138-qkc0drb",
          "lot": "CN-NW-BKR-1787",
          "location": "西安",
          "timestamp": 1766903016138,
          "assetId": "bot_asset_1764815086034_e3zax4p",
          "nodeName": "XI'AN (Urban Reserve)",
          "nodeLocation": {
            "lat": 34.30677307704516,
            "lng": 108.98476437795821
          },
          "value": 275,
          "status": "pending"
        },
        {
          "id": "1766903014882-ddxht6u",
          "lot": "CN-INT-BKR-4562",
          "location": "延安",
          "timestamp": 1766903014882,
          "assetId": "bot_asset_1764692014768_haxnips",
          "nodeName": "SHAANXI (Qinling Base)",
          "nodeLocation": {
            "lat": 33.86668277069271,
            "lng": 110.18932899651826
          },
          "value": 254,
          "status": "pending"
        },
        {
          "id": "1766903014284-4h05ogn",
          "lot": "CN-QINLING-CMD-7221",
          "location": "商洛",
          "timestamp": 1766903014284,
          "assetId": "bot_asset_1764772565406_f5v5jbf",
          "nodeName": "SHAANXI (Qinling Base)",
          "nodeLocation": {
            "lat": 33.867258295264094,
            "lng": 110.17954512432533
          },
          "value": 72,
          "status": "pending"
        },
        {
          "id": "1766903013671-q1gmgg4",
          "lot": "CN-INT-CMD-1205",
          "location": "安康",
          "timestamp": 1766903013671,
          "assetId": "bot_asset_1764827773035_vzuthj8",
          "nodeName": "SHAANXI (Qinling Base)",
          "nodeLocation": {
            "lat": 33.833039272525696,
            "lng": 110.11798422283609
          },
          "value": 141,
          "status": "pending"
        },
        {
          "id": "1766903013063-hsrkybw",
          "lot": "CN-INT-CMD-1205",
          "location": "安康",
          "timestamp": 1766903013063,
          "assetId": "bot_asset_1764827773035_vzuthj8",
          "nodeName": "SHAANXI (Qinling Base)",
          "nodeLocation": {
            "lat": 33.830162763013156,
            "lng": 110.17799895035861
          },
          "value": 141,
          "status": "pending"
        }
      ]
    },
    "blockHeight": "8922104"
  }
}